barotropy/__init__.py
barotropy/barotropic_model.py
barotropy/fluent_automation/__init__.py
barotropy/fluent_automation/fluent_automation.py
barotropy/fluent_automation/fluent_plot_nozzle_data.py
barotropy/fluent_automation/isentropic_nozzle.py
barotropy/fluent_automation/nozzle_meshing.py
barotropy/fluent_automation/stream_residuals.py
barotropy/fluent_automation/stream_transcript.py
barotropy/graphics.py
barotropy/math.py
barotropy/matlab/FluidCoolProp_2Phase.m
barotropy/matlab/compute_pseudocritical_line.m
barotropy/matlab/compute_pseudocritical_point.m
barotropy/matlab/compute_saturation_line.m
barotropy/matlab/compute_saturation_point_entropy.m
barotropy/matlab/compute_spinodal_line.m
barotropy/matlab/compute_spinodal_point.m
barotropy/matlab/compute_spinodal_point_entropy.m
barotropy/matlab/create_barotropic_model.m
barotropy/matlab/create_barotropic_model_segment.m
barotropy/matlab/evaluate_isentrope_polynomials.m
barotropy/matlab/export_fluent_expressions.m
barotropy/matlab/plot_barotropic_model.m
barotropy/matlab/plot_barotropic_polynomials.m
barotropy/matlab/plot_barotropic_process_ps.m
barotropy/matlab/plot_phase_diagram.m
barotropy/matlab/set_plot_options.m
barotropy/utilities.py
barotropy-0.4.1.dist-info/LICENSE.md
barotropy-0.4.1.dist-info/METADATA
barotropy-0.4.1.dist-info/WHEEL
barotropy-0.4.1.dist-info/RECORD
