Metadata-Version: 2.1
Name: barotropy
Version: 0.4.1
Summary: A Python tool for barotropic fluid property modeling.
Home-page: https://github.com/turbo-sim/barotropy
License: MIT
Author: Roberto Agromayor
Requires-Python: >=3.10,<3.14
Classifier: License :: OSI Approved :: MIT License
Classifier: Programming Language :: Python :: 3
Classifier: Programming Language :: Python :: 3.10
Classifier: Programming Language :: Python :: 3.11
Classifier: Programming Language :: Python :: 3.12
Provides-Extra: gmsh
Provides-Extra: pyfluent
Requires-Dist: PyYAML (>=6.0.2,<7.0.0)
Requires-Dist: ansys-fluent-core (>=0.30.2,<0.31.0) ; extra == "pyfluent"
Requires-Dist: coolpropx (>=0.2.20,<0.3.0)
Requires-Dist: cycler (>=0.12.1,<0.13.0)
Requires-Dist: gmsh (>=4.14.0,<5.0.0) ; extra == "gmsh"
Requires-Dist: matplotlib (>=3.10.1,<4.0.0)
Requires-Dist: numpy (>=2.2.4,<3.0.0)
Requires-Dist: openpyxl (>=3.1.5,<4.0.0)
Requires-Dist: pandas (>=2.2.3,<3.0.0)
Requires-Dist: parse (>=1.20.2,<2.0.0)
Requires-Dist: pexpect (>=4.9.0,<5.0.0)
Requires-Dist: pysolver_view (>=0.6.2,<0.7.0)
Requires-Dist: scipy (>=1.15.2,<2.0.0)
Requires-Dist: toml (>=0.10.2,<0.11.0)
Project-URL: Documentation, https://turbo-sim.github.io/barotropy/
Project-URL: Repository, https://github.com/turbo-sim/barotropy
